HiCExplorer-2.2.1.1.data/scripts/chicAggregateStatistic
HiCExplorer-2.2.1.1.data/scripts/chicDifferentialTest
HiCExplorer-2.2.1.1.data/scripts/chicPlotViewpoint
HiCExplorer-2.2.1.1.data/scripts/chicViewpoint
HiCExplorer-2.2.1.1.data/scripts/chicViewpointBackgroundModel
HiCExplorer-2.2.1.1.data/scripts/findRestSite
HiCExplorer-2.2.1.1.data/scripts/hicAdjustMatrix
HiCExplorer-2.2.1.1.data/scripts/hicAggregateContacts
HiCExplorer-2.2.1.1.data/scripts/hicAverageRegions
HiCExplorer-2.2.1.1.data/scripts/hicBuildMatrix
HiCExplorer-2.2.1.1.data/scripts/hicCompareMatrices
HiCExplorer-2.2.1.1.data/scripts/hicConvertFormat
HiCExplorer-2.2.1.1.data/scripts/hicCorrectMatrix
HiCExplorer-2.2.1.1.data/scripts/hicCorrelate
HiCExplorer-2.2.1.1.data/scripts/hicDetectLoops
HiCExplorer-2.2.1.1.data/scripts/hicDifferentialAnalysis
HiCExplorer-2.2.1.1.data/scripts/hicExport
HiCExplorer-2.2.1.1.data/scripts/hicFindEnrichedContacts
HiCExplorer-2.2.1.1.data/scripts/hicFindTADs
HiCExplorer-2.2.1.1.data/scripts/hicInfo
HiCExplorer-2.2.1.1.data/scripts/hicLog2Ratio
HiCExplorer-2.2.1.1.data/scripts/hicMergeMatrixBins
HiCExplorer-2.2.1.1.data/scripts/hicNormalize
HiCExplorer-2.2.1.1.data/scripts/hicPCA
HiCExplorer-2.2.1.1.data/scripts/hicPlotAverageRegions
HiCExplorer-2.2.1.1.data/scripts/hicPlotDistVsCounts
HiCExplorer-2.2.1.1.data/scripts/hicPlotMatrix
HiCExplorer-2.2.1.1.data/scripts/hicPlotTADs
HiCExplorer-2.2.1.1.data/scripts/hicPlotViewpoint
HiCExplorer-2.2.1.1.data/scripts/hicQC
HiCExplorer-2.2.1.1.data/scripts/hicSumMatrices
HiCExplorer-2.2.1.1.data/scripts/hicTransform
HiCExplorer-2.2.1.1.data/scripts/hicexplorer
hicexplorer/__init__.py
hicexplorer/_version.py
hicexplorer/chicAggregateStatistic.py
hicexplorer/chicCorrectMatrix.py
hicexplorer/chicDifferentialAnalysis.py
hicexplorer/chicDifferentialTest.py
hicexplorer/chicPlotViewpoint.py
hicexplorer/chicViewpoint.py
hicexplorer/chicViewpointBackgroundModel.py
hicexplorer/findRestSite.py
hicexplorer/hicAdjustMatrix.py
HiCExplorer-2.2.1.1.dist-info/LICENSE
HiCExplorer-2.2.1.1.dist-info/METADATA
HiCExplorer-2.2.1.1.dist-info/WHEEL
HiCExplorer-2.2.1.1.dist-info/top_level.txt
HiCExplorer-2.2.1.1.dist-info/RECORD
