Metadata-Version: 2.1
Name: HiCExplorer
Version: 2.2.1.1
Summary: Set of programs to process, analyze and visualize Hi-C data
Home-page: http://hicexplorer.readthedocs.io
Author: Fidel Ramirez, Vivek Bhardwaj, Björn Grüning, Joachim Wolff
Author-email: deeptools@googlegroups.com
License: LICENSE.txt
Platform: UNKNOWN
Classifier: Intended Audience :: Science/Research
Classifier: Topic :: Scientific/Engineering :: Bio-Informatics
Requires-Dist: numpy (>=1.15.*)
Requires-Dist: scipy (>=1.1.*)
Requires-Dist: matplotlib (>2.2.*)
Requires-Dist: pysam (>=0.14)
Requires-Dist: intervaltree (==2.1.*)
Requires-Dist: biopython (>=1.72)
Requires-Dist: tables (>=3.4.*)
Requires-Dist: pandas (>=0.23.*)
Requires-Dist: pyBigWig (>=0.3.*)
Requires-Dist: six (>=1.11.*)
Requires-Dist: future (>=0.17.*)
Requires-Dist: cooler (==0.8.2)
Requires-Dist: jinja2 (>=2.10.*)
Requires-Dist: unidecode (>=1.0.*)
Requires-Dist: hicmatrix (>=7)
Requires-Dist: pygenometracks (>=2.1)
Requires-Dist: psutil (>=5.4.8)
Requires-Dist: hic2cool (>=0.4)
Requires-Dist: configparser (==3.5.*)
